setup.py
url_archiver/__init__.py
url_archiver/url_archiver.py
urlarchiver.egg-info/PKG-INFO
urlarchiver.egg-info/SOURCES.txt
urlarchiver.egg-info/dependency_links.txt
urlarchiver.egg-info/requires.txt
urlarchiver.egg-info/top_level.txt