Metadata-Version: 1.0
Name: urlarchiver
Version: 0.1
Summary: url-archiver is a simple library to fetch and archive URL on the file-system.
Home-page: http://github.com/adulau/url_archiver
Author: Alexandre Dulaunoy
Author-email: a@foo.be
License: AGPL
Keywords: internet url caching webcache cache
Platform: UNKNOWN
